odoo/addons/base_geoengine_demo/README.rst
odoo/addons/base_geoengine_demo/__init__.py
odoo/addons/base_geoengine_demo/__manifest__.py
odoo/addons/base_geoengine_demo/data/npa_geom.xml
odoo/addons/base_geoengine_demo/data/retail_machine_geom.xml
odoo/addons/base_geoengine_demo/i18n/base_geoengine_demo.pot
odoo/addons/base_geoengine_demo/images/map-hover.png
odoo/addons/base_geoengine_demo/images/map.png
odoo/addons/base_geoengine_demo/models/__init__.py
odoo/addons/base_geoengine_demo/models/geo_npa.py
odoo/addons/base_geoengine_demo/models/retail_machine.py
odoo/addons/base_geoengine_demo/readme/CONTRIBUTORS.rst
odoo/addons/base_geoengine_demo/readme/DESCRIPTION.rst
odoo/addons/base_geoengine_demo/readme/INSTALL.rst
odoo/addons/base_geoengine_demo/readme/USAGE.rst
odoo/addons/base_geoengine_demo/security/ir.model.access.csv
odoo/addons/base_geoengine_demo/static/description/icon.png
odoo/addons/base_geoengine_demo/static/description/index.html
odoo/addons/base_geoengine_demo/views/menus.xml
odoo/addons/base_geoengine_demo/views/retail_machine.xml
odoo/addons/base_geoengine_demo/views/zip.xml
odoo12_addon_base_geoengine_demo-12.0.1.0.3.dist-info/METADATA
odoo12_addon_base_geoengine_demo-12.0.1.0.3.dist-info/WHEEL
odoo12_addon_base_geoengine_demo-12.0.1.0.3.dist-info/top_level.txt
odoo12_addon_base_geoengine_demo-12.0.1.0.3.dist-info/RECORD
